stlbs/__init__.py
stlbs/api.py
stlbs/exceptions/__init__.py
stlbs/tests/__init__.py
stlbs/tests/test_all.py
stlbs-1.0.2.dist-info/LICENSE
stlbs-1.0.2.dist-info/METADATA
stlbs-1.0.2.dist-info/WHEEL
stlbs-1.0.2.dist-info/top_level.txt
stlbs-1.0.2.dist-info/RECORD
