Metadata-Version: 2.1
Name: stlbs
Version: 1.0.2
Summary: A datatype to make using stones and pounds easier
Author-email: Rich Cairns <richard.a.cairnsNOSPAM@gmail.com>
License: MIT License        
Project-URL: Homepage, https://github.com/rogfrich/stlbs
Keywords: weight,mass,stones,pounds,lbs,stones and pounds
Classifier: License :: OSI Approved :: MIT License
Classifier: Programming Language :: Python
Classifier: Programming Language :: Python :: 3
Requires-Python: >=3.9
License-File: LICENSE
Provides-Extra: dev
Requires-Dist: bumpver ; extra == 'dev'
Requires-Dist: black ; extra == 'dev'
Requires-Dist: pytest ; extra == 'dev'
Requires-Dist: twine ; extra == 'dev'
